{
    "amqp": {
        "source_type": "archive",
        "filename": "amqp.tgz",
        "move_path": "php-src/ext/amqp",
        "lock_as": 1
    },
    "apcu": {
        "source_type": "archive",
        "filename": "apcu.tgz",
        "move_path": "php-src/ext/apcu",
        "lock_as": 1
    },
    "brotli": {
        "source_type": "archive",
        "filename": "google-brotli-dev-null-0-g91d1b2d.tar.gz",
        "move_path": null,
        "lock_as": 1
    },
    "bzip2": {
        "source_type": "archive",
        "filename": "bzip2-1.0.8.tar.gz",
        "move_path": null,
        "lock_as": 1
    },
    "curl": {
        "source_type": "archive",
        "filename": "curl-8.11.0.tar.xz",
        "move_path": null,
        "lock_as": 1
    },
    "ext-ds": {
        "source_type": "archive",
        "filename": "ds.tgz",
        "move_path": "php-src/ext/ds",
        "lock_as": 1
    },
    "ext-event": {
        "source_type": "archive",
        "filename": "3.0.8.tar.gz",
        "move_path": "php-src/ext/event",
        "lock_as": 1
    },
    "ext-glfw": {
        "source_type": "dir",
        "dirname": "ext-glfw",
        "move_path": null,
        "lock_as": 1
    },
    "ext-gmssl": {
        "source_type": "archive",
        "filename": "GmSSL-GmSSL-PHP-v1.1.0-0-g36055bd.tar.gz",
        "move_path": "php-src/ext/gmssl",
        "lock_as": 1
    },
    "ext-imagick": {
        "source_type": "archive",
        "filename": "imagick.tgz",
        "move_path": "php-src/ext/imagick",
        "lock_as": 1
    },
    "ext-memcache": {
        "source_type": "archive",
        "filename": "memcache.tgz",
        "move_path": "php-src/ext/memcache",
        "lock_as": 1
    },
    "ext-simdjson": {
        "source_type": "archive",
        "filename": "simdjson.tgz",
        "move_path": "php-src/ext/simdjson",
        "lock_as": 1
    },
    "ext-snappy": {
        "source_type": "dir",
        "dirname": "ext-snappy",
        "move_path": "php-src/ext/snappy",
        "lock_as": 1
    },
    "ext-ssh2": {
        "source_type": "archive",
        "filename": "ssh2.tgz",
        "move_path": "php-src/ext/ssh2",
        "lock_as": 1
    },
    "ext-uuid": {
        "source_type": "archive",
        "filename": "uuid.tgz",
        "move_path": "php-src/ext/uuid",
        "lock_as": 1
    },
    "ext-uv": {
        "source_type": "archive",
        "filename": "uv.tgz",
        "move_path": "php-src/ext/uv",
        "lock_as": 1
    },
    "ext-zstd": {
        "source_type": "dir",
        "dirname": "ext-zstd",
        "move_path": "php-src/ext/zstd",
        "lock_as": 1
    },
    "freetype": {
        "source_type": "dir",
        "dirname": "freetype",
        "move_path": null,
        "lock_as": 1
    },
    "gettext": {
        "source_type": "archive",
        "filename": "gettext-0.22.5.tar.xz",
        "move_path": null,
        "lock_as": 1
    },
    "gmp": {
        "source_type": "archive",
        "filename": "gmp-6.3.0.tar.xz",
        "move_path": null,
        "lock_as": 1
    },
    "gmssl": {
        "source_type": "archive",
        "filename": "guanzhi-GmSSL-v3.1.1-0-gd655c06.tar.gz",
        "move_path": null,
        "lock_as": 1
    },
    "icu": {
        "source_type": "archive",
        "filename": "icu4c-76_1-src.tgz",
        "move_path": null,
        "lock_as": 1
    },
    "igbinary": {
        "source_type": "archive",
        "filename": "igbinary.tgz",
        "move_path": "php-src/ext/igbinary",
        "lock_as": 1
    },
    "imagemagick": {
        "source_type": "archive",
        "filename": "ImageMagick-ImageMagick-7.1.1-41-0-gbbdcbf7.tar.gz",
        "move_path": null,
        "lock_as": 1
    },
    "imap": {
        "source_type": "dir",
        "dirname": "imap",
        "move_path": null,
        "lock_as": 1
    },
    "inotify": {
        "source_type": "archive",
        "filename": "inotify.tgz",
        "move_path": "php-src/ext/inotify",
        "lock_as": 1
    },
    "ldap": {
        "source_type": "archive",
        "filename": "openldap-2.6.8.tgz",
        "move_path": null,
        "lock_as": 1
    },
    "libargon2": {
        "source_type": "dir",
        "dirname": "libargon2",
        "move_path": null,
        "lock_as": 1
    },
    "libavif": {
        "source_type": "archive",
        "filename": "AOMediaCodec-libavif-v1.1.1-0-gbb24db0.tar.gz",
        "move_path": null,
        "lock_as": 1
    },
    "libcares": {
        "source_type": "archive",
        "filename": "c-ares-1.34.3.tar.gz",
        "move_path": null,
        "lock_as": 1
    },
    "libevent": {
        "source_type": "archive",
        "filename": "libevent-2.1.12-stable.tar.gz",
        "move_path": null,
        "lock_as": 1
    },
    "libffi": {
        "source_type": "archive",
        "filename": "libffi-3.4.6.tar.gz",
        "move_path": null,
        "lock_as": 1
    },
    "libffi-win": {
        "source_type": "dir",
        "dirname": "libffi-win",
        "move_path": null,
        "lock_as": 1
    },
    "libiconv": {
        "source_type": "archive",
        "filename": "libiconv-1.17.tar.gz",
        "move_path": null,
        "lock_as": 1
    },
    "libiconv-win": {
        "source_type": "dir",
        "dirname": "libiconv-win",
        "move_path": null,
        "lock_as": 1
    },
    "libjpeg": {
        "source_type": "archive",
        "filename": "libjpeg-turbo-libjpeg-turbo-3.0.90-0-ga9f7490.tar.gz",
        "move_path": null,
        "lock_as": 1
    },
    "liblz4": {
        "source_type": "archive",
        "filename": "lz4-1.10.0.tar.gz",
        "move_path": null,
        "lock_as": 1
    },
    "libmemcached": {
        "source_type": "dir",
        "dirname": "libmemcached",
        "move_path": null,
        "lock_as": 1
    },
    "libpng": {
        "source_type": "dir",
        "dirname": "libpng",
        "move_path": null,
        "lock_as": 1
    },
    "librabbitmq": {
        "source_type": "dir",
        "dirname": "librabbitmq",
        "move_path": null,
        "lock_as": 1
    },
    "libsodium": {
        "source_type": "archive",
        "filename": "libsodium-1.0.20.tar.gz",
        "move_path": null,
        "lock_as": 1
    },
    "libssh2": {
        "source_type": "archive",
        "filename": "libssh2-1.11.1.tar.gz",
        "move_path": null,
        "lock_as": 1
    },
    "libtiff": {
        "source_type": "archive",
        "filename": "tiff-4.7.0.tar.xz",
        "move_path": null,
        "lock_as": 1
    },
    "libuuid": {
        "source_type": "dir",
        "dirname": "libuuid",
        "move_path": null,
        "lock_as": 1
    },
    "libuv": {
        "source_type": "archive",
        "filename": "libuv-libuv-v1.49.2-0-ge1095c7.tar.gz",
        "move_path": null,
        "lock_as": 1
    },
    "libwebp": {
        "source_type": "archive",
        "filename": "v1.3.2.tar.gz",
        "move_path": null,
        "lock_as": 1
    },
    "libxml2": {
        "source_type": "archive",
        "filename": "v2.12.5.tar.gz",
        "move_path": null,
        "lock_as": 1
    },
    "libxslt": {
        "source_type": "archive",
        "filename": "libxslt-1.1.42.tar.xz",
        "move_path": null,
        "lock_as": 1
    },
    "libyaml": {
        "source_type": "archive",
        "filename": "yaml-0.2.5.tar.gz",
        "move_path": null,
        "lock_as": 1
    },
    "libzip": {
        "source_type": "archive",
        "filename": "libzip-1.11.2.tar.xz",
        "move_path": null,
        "lock_as": 1
    },
    "memcached": {
        "source_type": "archive",
        "filename": "memcached.tgz",
        "move_path": "php-src/ext/memcached",
        "lock_as": 1
    },
    "micro": {
        "source_type": "dir",
        "dirname": "micro",
        "move_path": "php-src/sapi/micro",
        "lock_as": 1
    },
    "mongodb": {
        "source_type": "archive",
        "filename": "mongodb-1.20.0.tgz",
        "move_path": "php-src/ext/mongodb",
        "lock_as": 1
    },
    "msgpack": {
        "source_type": "archive",
        "filename": "msgpack.tgz",
        "move_path": "php-src/ext/msgpack",
        "lock_as": 1
    },
    "ncurses": {
        "source_type": "archive",
        "filename": "ncurses-6.5.tar.gz",
        "move_path": null,
        "lock_as": 1
    },
    "nghttp2": {
        "source_type": "archive",
        "filename": "nghttp2-1.64.0.tar.xz",
        "move_path": null,
        "lock_as": 1
    },
    "onig": {
        "source_type": "archive",
        "filename": "onig-6.9.9.tar.gz",
        "move_path": null,
        "lock_as": 1
    },
    "openssl": {
        "source_type": "archive",
        "filename": "openssl-3.4.0.tar.gz",
        "move_path": null,
        "lock_as": 1
    },
    "parallel": {
        "source_type": "archive",
        "filename": "parallel.tgz",
        "move_path": "php-src/ext/parallel",
        "lock_as": 1
    },
    "pdo_sqlsrv": {
        "source_type": "archive",
        "filename": "pdo_sqlsrv.tgz",
        "move_path": "php-src/ext/pdo_sqlsrv",
        "lock_as": 1
    },
    "pkg-config": {
        "source_type": "archive",
        "filename": "pkg-config-0.29.2.tar.gz",
        "move_path": null,
        "lock_as": 1
    },
    "postgresql": {
        "source_type": "archive",
        "filename": "postgresql-16.2.tar.bz2",
        "move_path": null,
        "lock_as": 1
    },
    "protobuf": {
        "source_type": "archive",
        "filename": "protobuf.tgz",
        "move_path": "php-src/ext/protobuf",
        "lock_as": 1
    },
    "pthreads4w": {
        "source_type": "dir",
        "dirname": "pthreads4w",
        "move_path": null,
        "lock_as": 1
    },
    "qdbm": {
        "source_type": "dir",
        "dirname": "qdbm",
        "move_path": null,
        "lock_as": 1
    },
    "rar": {
        "source_type": "dir",
        "dirname": "rar",
        "move_path": "php-src/ext/rar",
        "lock_as": 1
    },
    "readline": {
        "source_type": "archive",
        "filename": "readline-8.2.13.tar.gz",
        "move_path": null,
        "lock_as": 1
    },
    "redis": {
        "source_type": "archive",
        "filename": "redis.tgz",
        "move_path": "php-src/ext/redis",
        "lock_as": 1
    },
    "snappy": {
        "source_type": "dir",
        "dirname": "snappy",
        "move_path": null,
        "lock_as": 1
    },
    "spx": {
        "source_type": "dir",
        "dirname": "spx",
        "move_path": "php-src/ext/spx",
        "lock_as": 1
    },
    "sqlite": {
        "source_type": "archive",
        "filename": "sqlite-autoconf-3430200.tar.gz",
        "move_path": null,
        "lock_as": 1
    },
    "sqlsrv": {
        "source_type": "archive",
        "filename": "sqlsrv.tgz",
        "move_path": "php-src/ext/sqlsrv",
        "lock_as": 1
    },
    "swoole": {
        "source_type": "archive",
        "filename": "swoole-swoole-src-v5.1.5-0-gc713f73.tar.gz",
        "move_path": "php-src/ext/swoole",
        "lock_as": 1
    },
    "swow": {
        "source_type": "dir",
        "dirname": "swow",
        "move_path": "php-src/ext/swow-src",
        "lock_as": 1
    },
    "tidy": {
        "source_type": "archive",
        "filename": "tidy-html5.tgz",
        "move_path": null,
        "lock_as": 1
    },
    "unixodbc": {
        "source_type": "archive",
        "filename": "unixODBC-2.3.12.tar.gz",
        "move_path": null,
        "lock_as": 1
    },
    "xhprof": {
        "source_type": "archive",
        "filename": "xhprof.tgz",
        "move_path": "php-src/ext/xhprof-src",
        "lock_as": 1
    },
    "xlswriter": {
        "source_type": "archive",
        "filename": "xlswriter.tgz",
        "move_path": "php-src/ext/xlswriter",
        "lock_as": 1
    },
    "xz": {
        "source_type": "archive",
        "filename": "xz-5.6.3.tar.xz",
        "move_path": null,
        "lock_as": 1
    },
    "yac": {
        "source_type": "archive",
        "filename": "yac.tgz",
        "move_path": "php-src/ext/yac",
        "lock_as": 1
    },
    "yaml": {
        "source_type": "dir",
        "dirname": "yaml",
        "move_path": "php-src/ext/yaml",
        "lock_as": 1
    },
    "zlib": {
        "source_type": "archive",
        "filename": "zlib-1.3.1.tar.gz",
        "move_path": null,
        "lock_as": 1
    },
    "zstd": {
        "source_type": "archive",
        "filename": "zstd-1.5.6.tar.gz",
        "move_path": null,
        "lock_as": 1
    },
    "ext-imap": {
        "source_type": "archive",
        "filename": "imap.tgz",
        "move_path": "php-src/ext/imap",
        "lock_as": 1
    },
    "grpc": {
        "source_type": "archive",
        "filename": "v1.68.0.zip",
        "move_path": null,
        "lock_as": 1
    },
    "upx-x86_64-linux": {
        "source_type": "archive",
        "filename": "upx-4.2.4-amd64_linux.tar.xz",
        "move_path": null,
        "lock_as": 2
    },
    "php-src": {
        "source_type": "archive",
        "filename": "php-8.3.14.tar.xz",
        "move_path": null,
        "lock_as": 1
    }
}